sudo/__init__.py
sudo/_hooks/__init__.py
sudo/_hooks/registration.py
sudo/_hooks/sdkhooks.py
sudo/_hooks/types.py
sudo/_version.py
sudo/basesdk.py
sudo/errors/__init__.py
sudo/errors/apierror.py
sudo/errors/errorresponse.py
sudo/errors/no_response_error.py
sudo/errors/responsevalidationerror.py
sudo/errors/sudoerror.py
sudo/httpclient.py
sudo/models/__init__.py
sudo/models/chatcompletion.py
sudo/models/chatcompletionchunk.py
sudo/models/chatcompletionchunkchoice.py
sudo/models/chatcompletiondelta.py
sudo/models/chatcompletionlist.py
sudo/models/chatcompletionrequestjson.py
sudo/models/chatcompletionrequeststream.py
sudo/models/chatdeletionconfirmation.py
sudo/models/chatmessage.py
sudo/models/chatmessagelist.py
sudo/models/choice.py
sudo/models/contentpart_union.py
sudo/models/deletechatcompletionop.py
sudo/models/errordetail.py
sudo/models/function.py
sudo/models/getchatcompletionmessagesop.py
sudo/models/getchatcompletionop.py
sudo/models/listchatcompletionsop.py
sudo/models/messagecontent.py
sudo/models/messageresponse.py
sudo/models/returnedchatmessages.py
sudo/models/security.py
sudo/models/supportedmodel.py
sudo/models/supportedmodelslist.py
sudo/models/tool.py
sudo/models/toolcall.py
sudo/models/toolcallfunction.py
sudo/models/updatechatcompletionop.py
sudo/models/usage.py
sudo/py.typed
sudo/router.py
sudo/sdk.py
sudo/sdkconfiguration.py
sudo/system.py
sudo/types/__init__.py
sudo/types/basemodel.py
sudo/utils/__init__.py
sudo/utils/annotations.py
sudo/utils/datetimes.py
sudo/utils/enums.py
sudo/utils/eventstreaming.py
sudo/utils/forms.py
sudo/utils/headers.py
sudo/utils/logger.py
sudo/utils/metadata.py
sudo/utils/queryparams.py
sudo/utils/requestbodies.py
sudo/utils/retries.py
sudo/utils/security.py
sudo/utils/serializers.py
sudo/utils/unmarshal_json_response.py
sudo/utils/url.py
sudo/utils/values.py
sudo_python-0.6.4.dist-info/METADATA
sudo_python-0.6.4.dist-info/WHEEL
sudo_python-0.6.4.dist-info/RECORD
